ppftps/__init__.py
ppftps-0.2.1.data/scripts/ppftps
ppftps-0.2.1.dist-info/METADATA
ppftps-0.2.1.dist-info/RECORD
ppftps-0.2.1.dist-info/WHEEL
ppftps-0.2.1.dist-info/dependency_links.txt
ppftps-0.2.1.dist-info/entry_points.txt
ppftps-0.2.1.dist-info/top_level.txt
