Metadata-Version: 2.1
Name: ppftps
Version: 0.2.1
Summary: Push directories over a secured FTP connection.
Home-page: https://github.com/studio-b12/ppftps
Author: Christoph Polcin
Author-email: c.polcin@studio-b12.de
License: BSD
Project-URL: Bug Reports, https://github.com/studio-b12/ppftps/issues
Project-URL: Source, https://github.com/studio-b12/ppftps
Keywords: cli ftp ftps keepass push pull sync util
Platform: UNKNOWN
Classifier: Development Status :: 3 - Alpha
Classifier: License :: OSI Approved :: BSD License
Classifier: Programming Language :: Python :: 3.6
Classifier: Topic :: Internet :: File Transfer Protocol (FTP)
Requires-Python: >=3
Requires-Dist: ftputil
